tc1_97
