Metadata-Version: 1.0
Name: ciefunctions
Version: 1.0.0b5
Summary: Desktop and web apps for computing the CIE Functions
Home-page: https://github.com/ifarup/ciefunctions
Author: Jan Henrik Wold and Ivar Farup
Author-email: ivar.farup@ntnu.no
License: GPL3.0
Platform: UNKNOWN
